{
  "timestamp": "20251103_154558",
  "total_tasks": 7,
  "tasks": [
    {
      "index": 1,
      "type": "Requirement",
      "content": "#### REQ-FUN-001: 空调系统控制\n*   **背景与上下文**: 车载空调系统是现代汽车的重要组成部分，用于调节车内温度和湿度，提供舒适的乘坐环境。\n*   **详细描述**: 系统应能够根据用户设定和外部环境自动调节车内温度，包括制冷、制热和除湿功能，并通过CAN总线与车辆其他系统（如导航、娱乐系统）进行数据交换。\n*   **技术参数和规格**:\n    - 制冷量：≥ 2.5 kW\n    - 制热量：≥ 2.0 kW\n    - 除湿量：≥ 1.5 kg/h\n    - 温度控制精度：±1°C\n*   **理由 (Rationale)**: 提高乘客舒适度，减少驾驶员分心，确保行车安全。\n*   **验证方法 (Verification)**: 测试、演示\n*   **优先级 (Priority)**: High\n\n---\n\n#### REQ-FUN-002: 温度控制精度\n*   **背景与上下文**: 精确的温度控制对于乘客的舒适度至关重要。\n*   **详细描述**: 系统应能够将车内温度控制在设定温度的±0.5°C范围内，并通过PID控制算法实现精确调节。\n*   **技术参数和规格**:\n    - 控制算法：PID\n    - 控制周期：1秒\n*   **理由 (Rationale)**: 提高用户满意度，确保系统性能。\n*   **验证方法 (Verification)**: 测试\n*   **优先级 (Priority)**: High\n\n---\n\n#### REQ-FUN-003: 能耗管理\n*   **背景与上下文**: 能耗管理对于提高燃油效率和减少排放至关重要。\n*   **详细描述**: 系统应通过智能算法优化制冷和制热过程，以最小化能耗，并实现节能模式。\n*   **技术参数和规格**:\n    - 节能模式能耗降低：≥ 20%\n*   **理由 (Rationale)**: 降低运营成本，减少环境影响。\n*   **验证方法 (Verification)**: 分析、测试\n*   **优先级 (Priority)**: Medium\n\n---\n\n#### REQ-NFN-001: 响应时间\n*   **背景与上下文**: 快速响应对于乘客舒适度和系统效率至关重要。\n*   **详细描述**: 系统在接收到温度调整指令后，应在2秒内开始响应，并通过实时监控确保系统响应时间不超过3秒。\n*   **技术参数和规格**:\n    - 响应时间：≤ 2秒\n*   **理由 (Rationale)**: 提高用户体验，确保系统效率。\n*   **验证方法 (Verification)**: 测试\n*   **优先级 (Priority)**: High\n\n---\n\n#### REQ-NFN-002: 系统可靠性\n*   **背景与上下文**: 空调系统需要长时间稳定运行，确保行车安全。\n*   **详细描述**: 系统的平均无故障时间（MTBF）应大于10,000小时，并通过冗余设计提高系统的可靠性。\n*   **技术参数和规格**:\n    - MTBF：≥ 10,000小时\n*   **理由 (Rationale)**: 提高系统可用性，减少维护成本。\n*   **验证方法 (Verification)**: 分析、测试\n*   **优先级 (Priority)**: High",
      "content_length": 1438
    },
    {
      "index": 2,
      "type": "Block Definition and Internal Block",
      "content": "### 2.1 系统顶层架构设计理念\n系统采用分层架构，分为用户界面层、控制层和执行层。用户界面层负责接收用户输入，控制层负责处理逻辑和决策，执行层负责执行具体的操作，并通过CAN总线实现各层之间的通信。\n\n---\n\n#### **块名称**: PowerControlModule\n*   **概述**: 负责控制空调系统的电源管理，包括启动、关闭和电源分配。\n*   **核心职责**:\n    - 启动和关闭空调系统\n    - 分配电源到各个子系统\n    - 监测电源状态\n*   **关键属性**:\n    - `- batteryLevel: Real [%] {0..100}`\n    - `- voltage: Volts`\n*   **核心操作**:\n    - `- enablePowerDistribution(voltage: Volts): Status`\n    - `- disablePowerDistribution(): Status`\n    - `- monitorPowerStatus(): PowerStatus'\n\n---\n\n#### **块名称**: TemperatureControlModule\n*   **概述**: 负责根据用户设定和外部环境调节车内温度。\n*   **核心职责**:\n    - 控制制冷和制热系统\n    - 调节风速和风向\n    - 监测车内温度\n*   **关键属性**:\n    - `- targetTemperature: Real [°C] {15..30}`\n    - `- currentTemperature: Real [°C] {15..30}`\n    - `- fanSpeed: Integer`\n*   **核心操作**:\n    - `- adjustTemperature(difference: Real [°C]): Status`\n    - `- setFanSpeed(speed: Integer): Status`\n    - `- monitorTemperature(): Real [°C]'\n\n---\n\n#### **块名称**: HumidityControlModule\n*   **概述**: 负责调节车内湿度，提供舒适的乘坐环境。\n*   **核心职责**:\n    - 控制除湿系统\n    - 监测车内湿度\n*   **关键属性**:\n    - `- targetHumidity: Real [%] {30..70}`\n    - `- currentHumidity: Real [%] {30..70}`\n*   **核心操作**:\n    - `- adjustHumidity(difference: Real [%]): Status`\n    - `- monitorHumidity(): Real [%]'\n\n---\n\n### 2.3 内部结构与交互原理 (Internal Block Diagram - IBD)\n#### **上下文**: PowerControlModule\n*   **设计阐述**: PowerControlModule通过CAN总线与TemperatureControlModule和HumidityControlModule通信，控制电源分配。\n*   **组成部分**:\n    - PowerControlModule\n    - TemperatureControlModule\n    - HumidityControlModule\n*   **连接关系**:\n    - `[PowerControlModule.portA] <--> [TemperatureControlModule.portB]`\n    - `[PowerControlModule.portC] <--> [HumidityControlModule.portD]'\n\n---\n\nHumidityControlModule\n*   **连接关系**:\n    - `[PowerControlModule.portA] <--> [TemperatureControlModule.portB]`\n    - `[PowerControlModule.portC] <--> [HumidityControlModule.portD]`",
      "content_length": 1867
    },
    {
      "index": 3,
      "type": "Activity",
      "content": "### 3.1 系统启动自检流程\n*   **流程概述**: 此流程描述了用户从按下开机按钮到系统进入待机状态的完整自检和初始化序列，确保所有硬件模块正常工作。\n*   **输入/输出**:\n    - IN: boot_command: Command\n    - OUT: system_status: StatusReport\n*   **步骤序列**:\n    1. 接收开机指令\n    2. 检查电源状态\n\n---\n\n### 3.1 系统启动自检流程\n*   **流程概述**: 此流程描述了用户从按下开机按钮到系统进入待机状态的完整自检和初始化序列，确保所有硬件模块正常工作。\n*   **输入/输出**:\n    - IN: boot_command: Command\n    - OUT: system_status: StatusReport\n*   **步骤序列**:\n    1. 接收开机指令\n    2. 检查电源状态\n    3. 检查传感器状态\n    4. 检查执行器状态\n    5. 初始化控制模块\n    6. 返回系统状态\n    7. 进入待机状态",
      "content_length": 496
    },
    {
      "index": 4,
      "type": "State Machine",
      "content": "### 4.1 空调系统状态机\n*   **上下文块**: AirConditioningSystem\n*   **行为模型概述**: 空调系统的行为模型定义了从‘关闭’到‘待机’再到‘运行’的完整生命周期，包括各种状态和转换条件。\n*   **状态定义**:\n    - **状态名称**: Off\n        *   **描述**: 空调系统关闭状态\n        *   `entry`: 关闭所有执行器\n        *   `do`: 无操作\n        *   `exit`: 无操作\n    - **状态名称**: Standby\n        *   **描述**: 空调系统待机状态\n        *   `entry`: 初始化传感器和执行器\n        *   `do`: 监测环境参数\n        *   `exit`: 无操作\n    - **状态名称**: Running\n        *   **描述**: 空调系统运行状态\n        *   `entry`: 启动制冷或制热系统\n        *   `do`: 调节温度和湿度\n        *   `exit`: 关闭制冷或制热系统\n*   **转换**:\n    - `Off --[power_on]--> Standby`\n    - `Standby --[temperature_change] / [humidity_change]--> Running`\n    - `Running --[power_off]--> Off`",
      "content_length": 683
    },
    {
      "index": 5,
      "type": "Use Case",
      "content": "### 5.1 用户控制空调系统\n*   **用例名称**: ControlAirConditioning\n*   **场景简述**: 用户通过车载触摸屏或物理按钮控制空调系统。\n*   **参与者**:\n    - Primary: 驾驶员\n    - Secondary: 车载触摸屏\n*   **基本流程**:\n    1. 驾驶员打开车载触摸屏\n    2. 驾驶员选择空调系统\n    3. 驾驶员设置目标温度和湿度\n    4. 系统开始调节温度和湿度\n    5. 系统显示当前温度和湿度\n    6. 驾驶员调整设置或关闭系统",
      "content_length": 271
    },
    {
      "index": 6,
      "type": "Parameter",
      "content": "### 6.1 温度控制方程\n*   **约束块**: TemperatureControlEquation\n*   **物理意义与应用**: 此方程用于计算空调系统达到目标温度所需的时间。\n*   **参数**:\n    - `T_current`: 当前温度 [°C]\n    - `T_target`: 目标温度 [°C]\n    - `Q`: 制冷或制热量 [W]\n    - `t`: 时间 [s]\n*   **约束公式**:\n    - `T_current + (Q * t) = T_target`",
      "content_length": 257
    },
    {
      "index": 7,
      "type": "Sequence",
      "content": "### 7.1 用户设置温度\n*   **场景名称**: UserSetsTemperature\n*   **交互背景**: 用户通过车载触摸屏设置目标温度。\n*   **涉及的生命线**:\n    - `[User]`\n    - `[TouchScreen]`\n    - `[AirConditioningSystem]`\n*   **消息序列**:\n    1. 用户在触摸屏上设置目标温度\n    2. 触摸屏发送温度设置到AirConditioningSystem\n    3. AirConditioningSystem调整制冷或制热系统以匹配目标温度\n    4. AirConditioningSystem向触摸屏发送当前温度和湿度信息\n    5. 触摸屏显示当前温度和湿度信息",
      "content_length": 349
    }
  ]
}